py_nacos_client/__init__.py
py_nacos_client/adapter_server.py
py_nacos_client/clienterror.py
py_nacos_client/logger.py
py_nacos_client/nacos_client.py
py_nacos_client/utils.py
jd_nacos_py-1.0.dist-info/LICENSE
jd_nacos_py-1.0.dist-info/METADATA
jd_nacos_py-1.0.dist-info/WHEEL
jd_nacos_py-1.0.dist-info/top_level.txt
jd_nacos_py-1.0.dist-info/RECORD
