Metadata-Version: 2.1
Name: jd-nacos-py
Version: 1.0
Summary: Python client for Nacos.
Home-page: UNKNOWN
Author: lijiarui
License: UNKNOWN
Keywords: jd_nacos_py
Platform: UNKNOWN
Requires-Python: >=3
License-File: LICENSE
Requires-Dist: nacos-sdk-python
